lousy_ai/__init__.py
lousy_ai/config.py
lousy_ai/orchestrator.py
lousy_ai/actions/__init__.py
lousy_ai/actions/append.py
lousy_ai/actions/base_action.py
lousy_ai/actions/copy.py
lousy_ai/actions/create.py
lousy_ai/actions/delete.py
lousy_ai/actions/list_dir.py
lousy_ai/actions/move.py
lousy_ai/actions/read.py
lousy_ai/actions/remove_dir.py
lousy_ai/actions/replace_lines.py
lousy_ai/actions/replace_regex.py
lousy_ai/actions/search.py
lousy_ai/files/__init__.py
lousy_ai/files/access.py
lousy_ai/files/atomic.py
lousy_ai/files/base_file.py
lousy_ai/rulesets/__init__.py
lousy_ai/rulesets/base_rule.py
lousy_ai/rulesets/follow.py
lousy_ai/rulesets/manage.py
lousy_ai/utils/__init__.py
lousy_ai/utils/data.py
lousy_ai/utils/function_finder.py
lousy_ai/utils/token.py
lousy_ai/worklog/__init__.py
lousy_ai/worklog/future.py
lousy_ai/worklog/history.py
lousy_ai/worklog/notes.py
lousy_ai/worklog/summary.py
lousy_ai/worklog/task.py
lousy_ai/worklog/versioning.py
lousy_ai-0.0.3.dist-info/METADATA
lousy_ai-0.0.3.dist-info/WHEEL
lousy_ai-0.0.3.dist-info/top_level.txt
lousy_ai-0.0.3.dist-info/RECORD
